conf2yaml/__init__.py
conf2yaml-0.0.2.dist-info/LICENSE
conf2yaml-0.0.2.dist-info/METADATA
conf2yaml-0.0.2.dist-info/WHEEL
conf2yaml-0.0.2.dist-info/top_level.txt
conf2yaml-0.0.2.dist-info/RECORD
